{
	"name": "filter_shorting",
	"properties": {
		"description": "sql to blob with filter and sorting",
		"type": "MappingDataFlow",
		"typeProperties": {
			"sources": [
				{
					"dataset": {
						"referenceName": "DS_Azuresql_P11",
						"type": "DatasetReference"
					},
					"name": "source1"
				}
			],
			"sinks": [
				{
					"dataset": {
						"referenceName": "DS_Blob_P11",
						"type": "DatasetReference"
					},
					"name": "sink1"
				}
			],
			"transformations": [
				{
					"name": "filter1"
				},
				{
					"name": "sort1"
				}
			],
			"scriptLines": [
				"source(output(",
				"          emp_id as integer,",
				"          emp_name as string,",
				"          emp_address as string,",
				"          gender as string",
				"     ),",
				"     allowSchemaDrift: true,",
				"     validateSchema: false,",
				"     isolationLevel: 'READ_UNCOMMITTED',",
				"     format: 'table') ~> source1",
				"source1 filter(gender == 'M') ~> filter1",
				"filter1 sort(asc(emp_id, true)) ~> sort1",
				"sort1 sink(allowSchemaDrift: true,",
				"     validateSchema: false,",
				"     skipDuplicateMapInputs: true,",
				"     skipDuplicateMapOutputs: true) ~> sink1"
			]
		}
	}
}